pyeCam.cp311-win_amd64.pyd
pyeCam-0.0.42.dist-info/METADATA
pyeCam-0.0.42.dist-info/WHEEL
pyeCam-0.0.42.dist-info/top_level.txt
pyeCam-0.0.42.dist-info/RECORD
