Metadata-Version: 2.1
Name: pyeCam
Version: 0.0.42
Summary: Example project using pybind11
Author: Your Name
Author-email: your_email@example.com
